[
  {
    "x": 0.6802,
    "y": 0.1122
  },
  {
    "x": 0.7276,
    "y": 0.1577
  },
  {
    "x": 0.7294,
    "y": 0.1663
  },
  {
    "x": 0.7176,
    "y": 0.1789
  },
  {
    "x": 0.6919,
    "y": 0.1846
  },
  {
    "x": 0.6685,
    "y": 0.1813
  },
  {
    "x": 0.612,
    "y": 0.1462
  },
  {
    "x": 0.5824,
    "y": 0.1429
  },
  {
    "x": 0.5435,
    "y": 0.1593
  },
  {
    "x": 0.5275,
    "y": 0.1768
  },
  {
    "x": 0.5211,
    "y": 0.1916
  },
  {
    "x": 0.5166,
    "y": 0.6306
  },
  {
    "x": 0.5265,
    "y": 0.6406
  },
  {
    "x": 0.6722,
    "y": 0.6391
  },
  {
    "x": 0.6898,
    "y": 0.6424
  },
  {
    "x": 0.7167,
    "y": 0.663
  },
  {
    "x": 0.7373,
    "y": 0.6937
  },
  {
    "x": 0.7423,
    "y": 0.721
  },
  {
    "x": 0.7418,
    "y": 0.7298
  },
  {
    "x": 0.7137,
    "y": 0.7373
  },
  {
    "x": 0.7069,
    "y": 0.7528
  },
  {
    "x": 0.7329,
    "y": 0.7977
  },
  {
    "x": 0.7305,
    "y": 0.8083
  },
  {
    "x": 0.7177,
    "y": 0.8151
  },
  {
    "x": 0.694,
    "y": 0.8173
  },
  {
    "x": 0.5162,
    "y": 0.8209
  },
  {
    "x": 0.4506,
    "y": 0.8286
  },
  {
    "x": 0.4289,
    "y": 0.8371
  },
  {
    "x": 0.405,
    "y": 0.857
  },
  {
    "x": 0.3529,
    "y": 0.95
  },
  {
    "x": 0.3327,
    "y": 0.9672
  },
  {
    "x": 0.2905,
    "y": 0.9852
  },
  {
    "x": 0.2142,
    "y": 0.999
  },
  {
    "x": 0.0895,
    "y": 0.8112
  },
  {
    "x": 0.0663,
    "y": 0.7687
  },
  {
    "x": 0.0248,
    "y": 0.6468
  },
  {
    "x": 0.0137,
    "y": 0.581
  },
  {
    "x": 0.0108,
    "y": 0.5309
  },
  {
    "x": 0.0119,
    "y": 0.3833
  },
  {
    "x": 0,
    "y": 0.0368
  },
  {
    "x": 0.0085,
    "y": 0.0313
  },
  {
    "x": 0.0288,
    "y": 0.0288
  },
  {
    "x": 0.0652,
    "y": 0.0053
  },
  {
    "x": 0.0878,
    "y": 0.0017
  },
  {
    "x": 0.4725,
    "y": 0.0013
  },
  {
    "x": 0.5592,
    "y": 0.0129
  },
  {
    "x": 0.58,
    "y": 0.0219
  },
  {
    "x": 0.6802,
    "y": 0.1122
  }
]